{
  "key": "agalactia",
  "source_file": "CIDE.A",
  "record_count": 1,
  "records": [
    {
      "headword": "agalactia",
      "headword_raw": "ag`a*lac\"ti*a",
      "pr": "(g`*lk\"t*)",
      "pos": [],
      "ety": null,
      "sources": [],
      "morph": null,
      "usage": [],
      "wordforms": [],
      "entry_synonyms": [],
      "entry_fields": [],
      "senses": [
        {
          "sn": "0",
          "fields": [],
          "defs": [],
          "quotes": [],
          "notes": [],
          "synonyms": []
        }
      ]
    }
  ]
}
