{
  "key": "alimony",
  "source_file": "CIDE.A",
  "record_count": 1,
  "records": [
    {
      "headword": "Alimony",
      "headword_raw": "Al\"i*mo*ny",
      "pr": "(<?/)",
      "pos": [
        "n."
      ],
      "ety": "[L. alimonia, alimonium, nourishment, sustenance, fr. alere to nourish.]",
      "sources": [
        "1913 Webster"
      ],
      "morph": null,
      "usage": [],
      "wordforms": [],
      "entry_synonyms": [],
      "entry_fields": [],
      "senses": [
        {
          "sn": "1.",
          "fields": [],
          "defs": [
            "Maintenance; means of living."
          ],
          "quotes": [],
          "notes": [],
          "synonyms": []
        },
        {
          "sn": "2.",
          "fields": [
            "(Law)"
          ],
          "defs": [
            "An allowance made to a wife out of her husband's estate or income for her support, upon her divorce or legal separation from him, or during a suit for the same."
          ],
          "quotes": [],
          "notes": [],
          "synonyms": []
        }
      ]
    }
  ]
}
