{
  "key": "allhallows",
  "source_file": "CIDE.A",
  "record_count": 1,
  "records": [
    {
      "headword": "Allhallows",
      "headword_raw": "All`hal\"lows",
      "pr": "(<?/)",
      "pos": [
        "n."
      ],
      "ety": null,
      "sources": [
        "1913 Webster"
      ],
      "morph": null,
      "usage": [],
      "wordforms": [],
      "entry_synonyms": [],
      "entry_fields": [],
      "senses": [
        {
          "sn": "1.",
          "fields": [],
          "defs": [
            "All the saints (in heaven)."
          ],
          "quotes": [],
          "notes": [],
          "synonyms": []
        },
        {
          "sn": "2.",
          "fields": [],
          "defs": [
            "All Saints' Day, November 1st."
          ],
          "quotes": [],
          "notes": [],
          "synonyms": []
        }
      ]
    }
  ]
}
