{
  "key": "annexation",
  "source_file": "CIDE.A",
  "record_count": 1,
  "records": [
    {
      "headword": "Annexation",
      "headword_raw": "An`nex*a\"tion",
      "pr": "(<?/)",
      "pos": [
        "n.",
        "v. t."
      ],
      "ety": "[Cf. F. annexation. See Annex, v. t.]",
      "sources": [
        "1913 Webster"
      ],
      "morph": null,
      "usage": [],
      "wordforms": [],
      "entry_synonyms": [],
      "entry_fields": [],
      "senses": [
        {
          "sn": "1.",
          "fields": [],
          "defs": [
            "The act of annexing; process of attaching, adding, or appending; the act of connecting; union; as, the annexation of Texas to the United States, or of chattels to the freehold."
          ],
          "quotes": [],
          "notes": [],
          "synonyms": []
        },
        {
          "sn": "2.",
          "fields": [
            "(Law)",
            "(Scots Law)"
          ],
          "defs": [
            "The union of property with a freehold so as to become a fixture. Bouvier. (b) (Scots Law) The appropriation of lands or rents to the crown."
          ],
          "quotes": [],
          "notes": [],
          "synonyms": []
        }
      ]
    }
  ]
}
