{
  "key": "appel",
  "source_file": "CIDE.A",
  "record_count": 1,
  "records": [
    {
      "headword": "Appel",
      "headword_raw": "Ap`pel\"",
      "pr": "(?)",
      "pos": [
        "n."
      ],
      "ety": "[F., prop., a call. See Appeal, n.]",
      "sources": [
        "Webster 1913 Suppl."
      ],
      "morph": null,
      "usage": [],
      "wordforms": [],
      "entry_synonyms": [],
      "entry_fields": [
        "(Fencing)"
      ],
      "senses": [
        {
          "sn": "0",
          "fields": [],
          "defs": [
            "A tap or stamp of the foot as a warning of intent to attack; -- called also attack."
          ],
          "quotes": [],
          "notes": [],
          "synonyms": []
        }
      ]
    }
  ]
}
