{
  "key": "archpriest",
  "source_file": "CIDE.A",
  "record_count": 1,
  "records": [
    {
      "headword": "Archpriest",
      "headword_raw": "Arch`priest\"",
      "pr": "(<?/)",
      "pos": [
        "n."
      ],
      "ety": null,
      "sources": [
        "1913 Webster"
      ],
      "morph": null,
      "usage": [],
      "wordforms": [],
      "entry_synonyms": [],
      "entry_fields": [],
      "senses": [
        {
          "sn": "0",
          "fields": [],
          "defs": [
            "A chief priest; also, a kind of vicar, or a rural dean."
          ],
          "quotes": [],
          "notes": [],
          "synonyms": []
        }
      ]
    }
  ]
}
