{
  "key": "autotrophic",
  "source_file": "CIDE.A",
  "record_count": 1,
  "records": [
    {
      "headword": "Autotrophic",
      "headword_raw": "Au`to*troph\"ic",
      "pr": "(?)",
      "pos": [
        "a."
      ],
      "ety": "[Auto- + trophic.]",
      "sources": [
        "Webster 1913 Suppl.",
        "WordNet 1.5"
      ],
      "morph": null,
      "usage": [],
      "wordforms": [],
      "entry_synonyms": [],
      "entry_fields": [
        "(Plant Physiol.)"
      ],
      "senses": [
        {
          "sn": "2.",
          "fields": [],
          "defs": [
            "of or pertaining to an autotroph."
          ],
          "quotes": [],
          "notes": [],
          "synonyms": []
        }
      ]
    }
  ]
}
