{
  "key": "becloud",
  "source_file": "CIDE.B",
  "record_count": 1,
  "records": [
    {
      "headword": "Becloud",
      "headword_raw": "Be*cloud\"",
      "pr": "(<?/)",
      "pos": [
        "v. t.",
        "imp. & p. p.",
        "p. pr. & vb. n."
      ],
      "ety": null,
      "sources": [
        "1913 Webster"
      ],
      "morph": "[imp. & p. p. Beclouded; p. pr. & vb. n. Beclouding.]",
      "usage": [],
      "wordforms": [],
      "entry_synonyms": [],
      "entry_fields": [],
      "senses": [
        {
          "sn": "0",
          "fields": [],
          "defs": [
            "To cause obscurity or dimness to; to dim; to cloud."
          ],
          "quotes": [
            "If thou becloud the sunshine of thine eye."
          ],
          "notes": [],
          "synonyms": []
        }
      ]
    }
  ]
}
