{
  "key": "brast",
  "source_file": "CIDE.B",
  "record_count": 1,
  "records": [
    {
      "headword": "Brast",
      "headword_raw": "Brast",
      "pr": "(<?/)",
      "pos": [
        "v. t. & i."
      ],
      "ety": "[See Burst.]",
      "sources": [
        "1913 Webster"
      ],
      "morph": null,
      "usage": [],
      "wordforms": [],
      "entry_synonyms": [],
      "entry_fields": [],
      "senses": [
        {
          "sn": "0",
          "fields": [],
          "defs": [
            "To burst."
          ],
          "quotes": [
            "And both his yën braste out of his face.",
            "Dreadfull furies which their chains have brast."
          ],
          "notes": [],
          "synonyms": []
        }
      ]
    }
  ]
}
