{
  "key": "collard",
  "source_file": "CIDE.C",
  "record_count": 1,
  "records": [
    {
      "headword": "collard",
      "headword_raw": "collard",
      "pr": null,
      "pos": [
        "n."
      ],
      "ety": null,
      "sources": [
        "WordNet 1.5",
        "+PJC"
      ],
      "morph": null,
      "usage": [],
      "wordforms": [],
      "entry_synonyms": [],
      "entry_fields": [],
      "senses": [
        {
          "sn": "1.",
          "fields": [],
          "defs": [
            "a variety of kale (Brassica oleracea) having smooth leaves; a type of colewort. It is grown in the southern U. S."
          ],
          "quotes": [],
          "notes": [],
          "synonyms": []
        }
      ]
    }
  ]
}
