{
  "key": "cosmopolite",
  "source_file": "CIDE.C",
  "record_count": 3,
  "records": [
    {
      "headword": "Cosmopolite",
      "headword_raw": "Cos*mop\"o*lite",
      "pr": "(k?z-m?p\"?-l?t)",
      "pos": [
        "n."
      ],
      "ety": "[Gr. kosmopoli`ths; ko`smos the world + poli`ths citizen, po`lis city: cf. F. cosmopolitain, cosmopolite.]",
      "sources": [
        "1913 Webster"
      ],
      "morph": null,
      "usage": [],
      "wordforms": [],
      "entry_synonyms": [],
      "entry_fields": [],
      "senses": [
        {
          "sn": "0",
          "fields": [],
          "defs": [
            "One who has no fixed residence, or who is at home in every place; a citizen of the world."
          ],
          "quotes": [],
          "notes": [],
          "synonyms": []
        }
      ]
    },
    {
      "headword": "Cosmopolite",
      "headword_raw": "Cos*mop\"o*lite",
      "pr": null,
      "pos": [
        "a."
      ],
      "ety": null,
      "sources": [
        "1913 Webster"
      ],
      "morph": null,
      "usage": [],
      "wordforms": [],
      "entry_synonyms": [],
      "entry_fields": [],
      "senses": [
        {
          "sn": "1.",
          "fields": [],
          "defs": [
            "Having no fixed residence; at home in any place; free from local attachments or prejudices; not provincial; liberal."
          ],
          "quotes": [
            "In other countries taste is perphaps too exclusively national, in Germany it is certainly too cosmopolite."
          ],
          "notes": [],
          "synonyms": []
        },
        {
          "sn": "2.",
          "fields": [],
          "defs": [
            "Common everywhere; widely spread; found in all parts of the world."
          ],
          "quotes": [
            "The Cheiroptera are cosmopolitan."
          ],
          "notes": [],
          "synonyms": []
        }
      ]
    },
    {
      "headword": "Cosmopolite",
      "headword_raw": "Cos*mop\"o*lite",
      "pr": "(-m?p\"?-l?t)",
      "pos": [
        "a. & n."
      ],
      "ety": null,
      "sources": [
        "1913 Webster"
      ],
      "morph": null,
      "usage": [],
      "wordforms": [],
      "entry_synonyms": [],
      "entry_fields": [],
      "senses": [
        {
          "sn": "0",
          "fields": [],
          "defs": [
            "See Cosmopolitan."
          ],
          "quotes": [],
          "notes": [],
          "synonyms": []
        }
      ]
    }
  ]
}
