{
  "key": "costage",
  "source_file": "CIDE.C",
  "record_count": 1,
  "records": [
    {
      "headword": "Costage",
      "headword_raw": "Cost\"age",
      "pr": "(k?st\"?j; 115)",
      "pos": [
        "n."
      ],
      "ety": "[OF. coustage.]",
      "sources": [
        "1913 Webster"
      ],
      "morph": null,
      "usage": [],
      "wordforms": [],
      "entry_synonyms": [],
      "entry_fields": [],
      "senses": [
        {
          "sn": "0",
          "fields": [],
          "defs": [
            "Expense; cost."
          ],
          "quotes": [],
          "notes": [],
          "synonyms": []
        }
      ]
    }
  ]
}
