{
  "key": "daddle",
  "source_file": "CIDE.D",
  "record_count": 1,
  "records": [
    {
      "headword": "Daddle",
      "headword_raw": "Dad\"dle",
      "pr": "(dd\"d'l)",
      "pos": [
        "v. i.",
        "imp. & p. p.",
        "p. pr. & vb. n."
      ],
      "ety": "[Prob. freq. of dade.]",
      "sources": [
        "1913 Webster"
      ],
      "morph": "[imp. & p. p. Daddled (?), p. pr. & vb. n. Daddling.]",
      "usage": [],
      "wordforms": [],
      "entry_synonyms": [],
      "entry_fields": [],
      "senses": [
        {
          "sn": "0",
          "fields": [],
          "defs": [
            "To toddle; to walk unsteadily, like a child or an old man; hence, to do anything slowly or feebly."
          ],
          "quotes": [],
          "notes": [],
          "synonyms": []
        }
      ]
    }
  ]
}
