{
  "key": "dumped",
  "source_file": "CIDE.D",
  "record_count": 1,
  "records": [
    {
      "headword": "dumped",
      "headword_raw": "dumped",
      "pr": null,
      "pos": [
        "adj.",
        "p. p.",
        "v. t."
      ],
      "ety": null,
      "sources": [
        "WordNet 1.5"
      ],
      "morph": null,
      "usage": [],
      "wordforms": [],
      "entry_synonyms": [],
      "entry_fields": [],
      "senses": [
        {
          "sn": "1.",
          "fields": [],
          "defs": [
            "p. p. of dump, v. t.; as, The money was there, dumped all over the floor."
          ],
          "quotes": [],
          "notes": [],
          "synonyms": []
        }
      ]
    }
  ]
}
