{
  "key": "dutchmans-breeches",
  "source_file": "CIDE.D",
  "record_count": 1,
  "records": [
    {
      "headword": "Dutchmans-breeches",
      "headword_raw": "Dutchman's-breeches",
      "pr": null,
      "pos": [
        "n."
      ],
      "ety": null,
      "sources": [
        "1913 Webster",
        "WordNet 1.5"
      ],
      "morph": null,
      "usage": [],
      "wordforms": [],
      "entry_synonyms": [
        "Dicentra cucullaria"
      ],
      "entry_fields": [
        "(Bot.)"
      ],
      "senses": [
        {
          "sn": "0",
          "fields": [],
          "defs": [
            "a delicate perennial spring-flowering herb (Dicentra cucullaria) of eastern U.S., having peculiar double-spurred white flowers. See Illust. of Dicentra"
          ],
          "quotes": [],
          "notes": [],
          "synonyms": []
        }
      ]
    }
  ]
}
