{
  "key": "evangely",
  "source_file": "CIDE.E",
  "record_count": 1,
  "records": [
    {
      "headword": "Evangely",
      "headword_raw": "E*van\"ge*ly",
      "pr": "(?)",
      "pos": [
        "n."
      ],
      "ety": null,
      "sources": [
        "1913 Webster"
      ],
      "morph": null,
      "usage": [],
      "wordforms": [],
      "entry_synonyms": [],
      "entry_fields": [],
      "senses": [
        {
          "sn": "0",
          "fields": [],
          "defs": [
            "Evangel."
          ],
          "quotes": [
            "The sacred pledge of Christ's evangely."
          ],
          "notes": [],
          "synonyms": []
        }
      ]
    }
  ]
}
