{
  "key": "fire_hydrant",
  "source_file": "CIDE.F",
  "record_count": 1,
  "records": [
    {
      "headword": "fire hydrant",
      "headword_raw": "fire hydrant",
      "pr": null,
      "pos": [
        "n."
      ],
      "ety": null,
      "sources": [
        "WordNet 1.5",
        "+PJC"
      ],
      "morph": null,
      "usage": [],
      "wordforms": [],
      "entry_synonyms": [
        "fireplug",
        "plug"
      ],
      "entry_fields": [],
      "senses": [
        {
          "sn": "0",
          "fields": [],
          "defs": [
            "an upright hydrant that can supply large volumes of water to use in fighting a fire. They are commonly placed at intervals at the street edge of a sidewalk, spaced for convenience in suppressing fires in towns."
          ],
          "quotes": [],
          "notes": [],
          "synonyms": []
        }
      ]
    }
  ]
}
