{
  "key": "guaiacum",
  "source_file": "CIDE.G",
  "record_count": 1,
  "records": [
    {
      "headword": "Guaiacum",
      "headword_raw": "Gua\"ia*cum",
      "pr": "(?)",
      "pos": [
        "n."
      ],
      "ety": "[NL., fr. Sp. guayaco, from native name in Haiti.]",
      "sources": [
        "1913 Webster"
      ],
      "morph": null,
      "usage": [],
      "wordforms": [],
      "entry_synonyms": [],
      "entry_fields": [],
      "senses": [
        {
          "sn": "1.",
          "fields": [
            "(Bot.)"
          ],
          "defs": [
            "A genus of small, crooked trees, growing in tropical America."
          ],
          "quotes": [],
          "notes": [],
          "synonyms": []
        },
        {
          "sn": "2.",
          "fields": [],
          "defs": [
            "The heart wood or the resin of the Guaiacum officinale or lignum-vitæ, a large tree of the West Indies and Central America. It is much used in medicine."
          ],
          "quotes": [],
          "notes": [],
          "synonyms": []
        }
      ]
    }
  ]
}
