{
  "key": "headlight",
  "source_file": "CIDE.H",
  "record_count": 1,
  "records": [
    {
      "headword": "Headlight",
      "headword_raw": "Head\"light`",
      "pr": "(hd\"līt`)",
      "pos": [
        "n."
      ],
      "ety": null,
      "sources": [
        "1913 Webster",
        "+PJC"
      ],
      "morph": null,
      "usage": [],
      "wordforms": [],
      "entry_synonyms": [],
      "entry_fields": [
        "(Engin.)"
      ],
      "senses": [
        {
          "sn": "0",
          "fields": [],
          "defs": [
            "A light, with a powerful reflector, placed at the front of a vehicle such as an automobile, truck, locomotive etc., to throw light on the road or track ahead of the vehicle at night, or in going through a dark tunnel; a headlamp."
          ],
          "quotes": [],
          "notes": [],
          "synonyms": []
        }
      ]
    }
  ]
}
