{
  "key": "holding",
  "source_file": "CIDE.H",
  "record_count": 1,
  "records": [
    {
      "headword": "Holding",
      "headword_raw": "Hold\"ing",
      "pr": null,
      "pos": [
        "n."
      ],
      "ety": null,
      "sources": [
        "1913 Webster"
      ],
      "morph": null,
      "usage": [],
      "wordforms": [],
      "entry_synonyms": [],
      "entry_fields": [],
      "senses": [
        {
          "sn": "1.",
          "fields": [],
          "defs": [
            "The act or state of sustaining, grasping, or retaining."
          ],
          "quotes": [],
          "notes": [],
          "synonyms": []
        },
        {
          "sn": "2.",
          "fields": [],
          "defs": [
            "A tenure; a farm or other estate held of another."
          ],
          "quotes": [],
          "notes": [],
          "synonyms": []
        },
        {
          "sn": "3.",
          "fields": [],
          "defs": [
            "That which holds, binds, or influences."
          ],
          "quotes": [],
          "notes": [],
          "synonyms": []
        },
        {
          "sn": "4.",
          "fields": [
            "(Mus.)"
          ],
          "defs": [
            "The burden or chorus of a song."
          ],
          "quotes": [],
          "notes": [],
          "synonyms": []
        }
      ]
    }
  ]
}
