{
  "key": "iguania",
  "source_file": "CIDE.I",
  "record_count": 1,
  "records": [
    {
      "headword": "Iguania",
      "headword_raw": "Iguania",
      "pr": null,
      "pos": [
        "n."
      ],
      "ety": null,
      "sources": [
        "WordNet 1.5"
      ],
      "morph": null,
      "usage": [],
      "wordforms": [],
      "entry_synonyms": [
        "family Iguania"
      ],
      "entry_fields": [],
      "senses": [
        {
          "sn": "0",
          "fields": [],
          "defs": [
            "A superfamily (or suborder) of New World lizards including the Iguanidae."
          ],
          "quotes": [],
          "notes": [],
          "synonyms": []
        }
      ]
    }
  ]
}
