{
  "key": "intervallum",
  "source_file": "CIDE.I",
  "record_count": 1,
  "records": [
    {
      "headword": "Intervallum",
      "headword_raw": "In`ter*val\"lum",
      "pr": "(?)",
      "pos": [
        "n."
      ],
      "ety": "[L.]",
      "sources": [
        "1913 Webster"
      ],
      "morph": null,
      "usage": [],
      "wordforms": [],
      "entry_synonyms": [],
      "entry_fields": [],
      "senses": [
        {
          "sn": "0",
          "fields": [],
          "defs": [
            "An interval."
          ],
          "quotes": [
            "And a' shall laugh without intervallums.",
            "In one of these intervalla."
          ],
          "notes": [],
          "synonyms": []
        }
      ]
    }
  ]
}
