{
  "key": "lament",
  "source_file": "CIDE.L",
  "record_count": 3,
  "records": [
    {
      "headword": "Lament",
      "headword_raw": "La*ment\"",
      "pr": "(?)",
      "pos": [
        "v. i."
      ],
      "ety": "[F. lamenter, L. lamentari, fr. lamentum a lament.]",
      "sources": [
        "1913 Webster"
      ],
      "morph": null,
      "usage": [],
      "wordforms": [],
      "entry_synonyms": [],
      "entry_fields": [],
      "senses": [
        {
          "sn": "0",
          "fields": [],
          "defs": [
            "To express or feel sorrow; to weep or wail; to mourn."
          ],
          "quotes": [
            "Jeremiah lamented for Josiah.",
            "Ye shall weep and lament, but the world shall rejoice."
          ],
          "notes": [],
          "synonyms": []
        }
      ]
    },
    {
      "headword": "Lament",
      "headword_raw": "La*ment\"",
      "pr": null,
      "pos": [
        "v. t.",
        "imp. & p. p.",
        "p. pr. & vb. n."
      ],
      "ety": null,
      "sources": [
        "1913 Webster"
      ],
      "morph": "[imp. & p. p. Lamented; p. pr. & vb. n. Lamenting.]",
      "usage": [],
      "wordforms": [],
      "entry_synonyms": [
        "deplore",
        "mourn",
        "bewail. See Deplore"
      ],
      "entry_fields": [],
      "senses": [
        {
          "sn": "0",
          "fields": [],
          "defs": [
            "To mourn for; to bemoan; to bewail."
          ],
          "quotes": [
            "One laughed at follies, one lamented crimes."
          ],
          "notes": [],
          "synonyms": []
        }
      ]
    },
    {
      "headword": "Lament",
      "headword_raw": "La*ment\"",
      "pr": null,
      "pos": [
        "n.",
        "v."
      ],
      "ety": "[L. lamentum. Cf. Lament, v.]",
      "sources": [
        "1913 Webster"
      ],
      "morph": null,
      "usage": [],
      "wordforms": [],
      "entry_synonyms": [],
      "entry_fields": [],
      "senses": [
        {
          "sn": "1.",
          "fields": [],
          "defs": [
            "Grief or sorrow expressed in complaints or cries; lamentation; a wailing; a moaning; a weeping."
          ],
          "quotes": [
            "Torment, and loud lament, and furious rage."
          ],
          "notes": [],
          "synonyms": []
        },
        {
          "sn": "2.",
          "fields": [],
          "defs": [
            "An elegy or mournful ballad, or the like."
          ],
          "quotes": [],
          "notes": [],
          "synonyms": []
        }
      ]
    }
  ]
}
