{
  "key": "li_bella",
  "source_file": "CIDE.L",
  "record_count": 1,
  "records": [
    {
      "headword": "Li bella",
      "headword_raw": "Li *bel\"la",
      "pr": "(l*bl\"l)",
      "pos": [
        "n."
      ],
      "ety": "[L., dim. of libra balance. See Level, n.]",
      "sources": [
        "1913 Webster"
      ],
      "morph": null,
      "usage": [],
      "wordforms": [],
      "entry_synonyms": [],
      "entry_fields": [],
      "senses": [
        {
          "sn": "1.",
          "fields": [],
          "defs": [
            "A small balance."
          ],
          "quotes": [],
          "notes": [],
          "synonyms": []
        },
        {
          "sn": "2.",
          "fields": [],
          "defs": [
            "A level, or leveling instrument."
          ],
          "quotes": [],
          "notes": [],
          "synonyms": []
        }
      ]
    }
  ]
}
