{
  "key": "manicotti",
  "source_file": "CIDE.M",
  "record_count": 1,
  "records": [
    {
      "headword": "manicotti",
      "headword_raw": "manicotti",
      "pr": null,
      "pos": [
        "n."
      ],
      "ety": null,
      "sources": [
        "WordNet 1.5",
        "+PJC"
      ],
      "morph": null,
      "usage": [],
      "wordforms": [],
      "entry_synonyms": [],
      "entry_fields": [],
      "senses": [
        {
          "sn": "0",
          "fields": [],
          "defs": [
            "Tubular large noodles that are usually stuffed with mild cheese and baked in tomato sauce; -- a type of Italian pasta; also a dish of such noodles thus prepared."
          ],
          "quotes": [],
          "notes": [],
          "synonyms": []
        }
      ]
    }
  ]
}
