{
  "key": "moliminous",
  "source_file": "CIDE.M",
  "record_count": 1,
  "records": [
    {
      "headword": "Moliminous",
      "headword_raw": "Mo*lim\"i*nous",
      "pr": "(?)",
      "pos": [
        "a."
      ],
      "ety": "[L. molimen a great exertion; moles a heavy mass.]",
      "sources": [
        "1913 Webster"
      ],
      "morph": null,
      "usage": [],
      "wordforms": [],
      "entry_synonyms": [],
      "entry_fields": [],
      "senses": [
        {
          "sn": "0",
          "fields": [],
          "defs": [
            "Of great bulk or consequence; very important."
          ],
          "quotes": [],
          "notes": [],
          "synonyms": []
        }
      ]
    }
  ]
}
