{
  "key": "mud",
  "source_file": "CIDE.M",
  "record_count": 2,
  "records": [
    {
      "headword": "Mud",
      "headword_raw": "Mud",
      "pr": "(md)",
      "pos": [
        "n."
      ],
      "ety": "[Akin to LG. mudde, D. modder, G. moder mold, OSw. modd mud, Sw. modder mother, Dan. mudder mud. Cf. Mother a scum on liquors.]",
      "sources": [
        "1913 Webster"
      ],
      "morph": null,
      "usage": [],
      "wordforms": [],
      "entry_synonyms": [],
      "entry_fields": [
        "(Zool.)",
        "(Zool.)",
        "(Zool.)",
        "(Zool.)",
        "(Zool.)",
        "(Steam Boilers)",
        "(Zool.)",
        "(Zool.)",
        "(Zool.)",
        "(Zool.)",
        "(Zool.)",
        "(Zool.)",
        "(Zool.)"
      ],
      "senses": [
        {
          "sn": "0",
          "fields": [],
          "defs": [
            "Earth and water mixed so as to be soft and adhesive."
          ],
          "quotes": [],
          "notes": [],
          "synonyms": []
        }
      ]
    },
    {
      "headword": "Mud",
      "headword_raw": "Mud",
      "pr": null,
      "pos": [
        "v. t."
      ],
      "ety": null,
      "sources": [
        "1913 Webster"
      ],
      "morph": null,
      "usage": [],
      "wordforms": [],
      "entry_synonyms": [],
      "entry_fields": [],
      "senses": [
        {
          "sn": "1.",
          "fields": [],
          "defs": [
            "To bury in mud."
          ],
          "quotes": [],
          "notes": [],
          "synonyms": []
        },
        {
          "sn": "2.",
          "fields": [],
          "defs": [
            "To make muddy or turbid."
          ],
          "quotes": [],
          "notes": [],
          "synonyms": []
        }
      ]
    }
  ]
}
