{
  "key": "nee",
  "source_file": "CIDE.N",
  "record_count": 1,
  "records": [
    {
      "headword": "Nee",
      "headword_raw": "Nee",
      "pr": "(n)",
      "pos": [
        "p. p., fem."
      ],
      "ety": "[F., fr. L. nata, fem. of natus, p. p. of nasci to be born. See Nation.]",
      "sources": [
        "1913 Webster"
      ],
      "morph": null,
      "usage": [],
      "wordforms": [],
      "entry_synonyms": [],
      "entry_fields": [],
      "senses": [
        {
          "sn": "0",
          "fields": [],
          "defs": [
            "Born; -- a term sometimes used in introducing the name of the family to which a married woman belongs by birth (i.e. her maiden name); as, Madame de Stael, ne Necker."
          ],
          "quotes": [],
          "notes": [],
          "synonyms": []
        }
      ]
    }
  ]
}
