{
  "key": "obolary",
  "source_file": "CIDE.O",
  "record_count": 1,
  "records": [
    {
      "headword": "Obolary",
      "headword_raw": "Ob\"o*la*ry",
      "pr": "(?)",
      "pos": [
        "a."
      ],
      "ety": "[See Obolus.]",
      "sources": [
        "1913 Webster"
      ],
      "morph": null,
      "usage": [],
      "wordforms": [],
      "entry_synonyms": [],
      "entry_fields": [],
      "senses": [
        {
          "sn": "0",
          "fields": [],
          "defs": [
            "Possessing only small coins; impoverished."
          ],
          "quotes": [],
          "notes": [],
          "synonyms": []
        }
      ]
    }
  ]
}
