{
  "key": "opossum",
  "source_file": "CIDE.O",
  "record_count": 1,
  "records": [
    {
      "headword": "Opossum",
      "headword_raw": "O*pos\"sum",
      "pr": "(?)",
      "pos": [
        "n."
      ],
      "ety": "[Of N. American Indian origin.]",
      "sources": [
        "1913 Webster"
      ],
      "morph": null,
      "usage": [],
      "wordforms": [],
      "entry_synonyms": [],
      "entry_fields": [
        "(Zool.)",
        "(Zool.)",
        "(Zool.)"
      ],
      "senses": [
        {
          "sn": "0",
          "fields": [],
          "defs": [
            "Any American marsupial of the genera Didelphys and Chironectes; called also possum. The common species of the United States is Didelphys Virginiana."
          ],
          "quotes": [],
          "notes": [
            "☞ Several related species are found in South America. The water opossum of Brazil (Chironectes variegatus), which has the hind feet, webbed, is provided with a marsupial pouch and with cheek pouches. It is called also yapock."
          ],
          "synonyms": []
        }
      ]
    }
  ]
}
