{
  "key": "organific",
  "source_file": "CIDE.O",
  "record_count": 1,
  "records": [
    {
      "headword": "Organific",
      "headword_raw": "Or`gan*if\"ic",
      "pr": "(?)",
      "pos": [
        "a."
      ],
      "ety": "[Organ + L. -ficare (in comp.) to make. See fy.]",
      "sources": [
        "1913 Webster"
      ],
      "morph": null,
      "usage": [],
      "wordforms": [],
      "entry_synonyms": [],
      "entry_fields": [],
      "senses": [
        {
          "sn": "0",
          "fields": [],
          "defs": [
            "Making an organic or organized structure; producing an organism; acting through, or resulting from, organs."
          ],
          "quotes": [],
          "notes": [],
          "synonyms": []
        }
      ]
    }
  ]
}
