{
  "key": "overstrew",
  "source_file": "CIDE.O",
  "record_count": 1,
  "records": [
    {
      "headword": "Overstrew",
      "headword_raw": "O`ver*strew\"",
      "pr": "(?)",
      "pos": [
        "v. t."
      ],
      "ety": null,
      "sources": [
        "1913 Webster"
      ],
      "morph": null,
      "usage": [],
      "wordforms": [],
      "entry_synonyms": [],
      "entry_fields": [],
      "senses": [
        {
          "sn": "0",
          "fields": [],
          "defs": [
            "To strew or scatter over."
          ],
          "quotes": [],
          "notes": [],
          "synonyms": []
        }
      ]
    }
  ]
}
