{
  "key": "phascolarctos",
  "source_file": "CIDE.P",
  "record_count": 1,
  "records": [
    {
      "headword": "Phascolarctos",
      "headword_raw": "Phascolarctos",
      "pr": null,
      "pos": [
        "prop. n."
      ],
      "ety": null,
      "sources": [
        "WordNet 1.5"
      ],
      "morph": null,
      "usage": [],
      "wordforms": [],
      "entry_synonyms": [
        "genus Phascolarctos"
      ],
      "entry_fields": [],
      "senses": [
        {
          "sn": "0",
          "fields": [],
          "defs": [
            "A genus of animals consisting of the koalas."
          ],
          "quotes": [],
          "notes": [],
          "synonyms": []
        }
      ]
    }
  ]
}
