{
  "key": "plenicorn",
  "source_file": "CIDE.P",
  "record_count": 1,
  "records": [
    {
      "headword": "Plenicorn",
      "headword_raw": "Ple\"ni*corn",
      "pr": "(plē\"n*krn)",
      "pos": [
        "n."
      ],
      "ety": "[L. plenus full + cornu horn.]",
      "sources": [
        "1913 Webster"
      ],
      "morph": null,
      "usage": [],
      "wordforms": [],
      "entry_synonyms": [],
      "entry_fields": [
        "(Zool.)"
      ],
      "senses": [
        {
          "sn": "0",
          "fields": [],
          "defs": [
            "A ruminant having solid horns or antlers, as the deer."
          ],
          "quotes": [],
          "notes": [],
          "synonyms": []
        }
      ]
    }
  ]
}
