{
  "key": "postanal",
  "source_file": "CIDE.P",
  "record_count": 1,
  "records": [
    {
      "headword": "Postanal",
      "headword_raw": "Post*a\"nal",
      "pr": "(?)",
      "pos": [
        "a."
      ],
      "ety": "[Pref. post- + anal.]",
      "sources": [
        "1913 Webster"
      ],
      "morph": null,
      "usage": [],
      "wordforms": [],
      "entry_synonyms": [],
      "entry_fields": [
        "(Anat.)"
      ],
      "senses": [
        {
          "sn": "0",
          "fields": [],
          "defs": [
            "Situated behind, or posterior to, the anus."
          ],
          "quotes": [],
          "notes": [],
          "synonyms": []
        }
      ]
    }
  ]
}
