{
  "key": "reflueus",
  "source_file": "CIDE.R",
  "record_count": 1,
  "records": [
    {
      "headword": "Reflueus",
      "headword_raw": "Ref\"lu*eus",
      "pr": "(-?s)",
      "pos": [
        "a."
      ],
      "ety": "[L. refluus.]",
      "sources": [
        "1913 Webster"
      ],
      "morph": null,
      "usage": [],
      "wordforms": [],
      "entry_synonyms": [],
      "entry_fields": [],
      "senses": [
        {
          "sn": "0",
          "fields": [],
          "defs": [
            "Refluent."
          ],
          "quotes": [],
          "notes": [],
          "synonyms": []
        }
      ]
    }
  ]
}
