{
  "key": "repartimiento",
  "source_file": "CIDE.R",
  "record_count": 1,
  "records": [
    {
      "headword": "Repartimiento",
      "headword_raw": "Re`par*ti`mi*en\"to",
      "pr": "(r?`p?r-t?`m?-?n\"t?)",
      "pos": [
        "n."
      ],
      "ety": "[Sp., fr. repartir to divide.]",
      "sources": [
        "1913 Webster"
      ],
      "morph": null,
      "usage": [],
      "wordforms": [],
      "entry_synonyms": [],
      "entry_fields": [],
      "senses": [
        {
          "sn": "0",
          "fields": [],
          "defs": [
            "A partition or distribution, especially of slaves; also, an assessment of taxes."
          ],
          "quotes": [],
          "notes": [],
          "synonyms": []
        }
      ]
    }
  ]
}
