{
  "key": "snail",
  "source_file": "CIDE.S",
  "record_count": 1,
  "records": [
    {
      "headword": "Snail",
      "headword_raw": "Snail",
      "pr": "(snāl)",
      "pos": [
        "n."
      ],
      "ety": "[OE. snaile, AS. snægel, snegel, snægl; akin to G. schnecke, OHG. snecko, Dan. snegl, Icel. snigill.]",
      "sources": [
        "1913 Webster"
      ],
      "morph": null,
      "usage": [],
      "wordforms": [],
      "entry_synonyms": [],
      "entry_fields": [],
      "senses": [
        {
          "sn": "1.",
          "fields": [
            "(Zool.)"
          ],
          "defs": [
            "Any one of numerous species of terrestrial air-breathing gastropods belonging to the genus Helix and many allied genera of the family Helicidae. They are abundant in nearly all parts of the world except the arctic regions, and feed almost entirely on vegetation; a land snail.",
            "Any gastropod having a general resemblance to the true snails, including fresh-water and marine species. See Pond snail, under Pond, and Sea snail."
          ],
          "quotes": [],
          "notes": [],
          "synonyms": []
        },
        {
          "sn": "2.",
          "fields": [],
          "defs": [
            "Hence, a drone; a slow-moving person or thing."
          ],
          "quotes": [],
          "notes": [],
          "synonyms": []
        },
        {
          "sn": "3.",
          "fields": [
            "(Mech.)"
          ],
          "defs": [
            "A spiral cam, or a flat piece of metal of spirally curved outline, used for giving motion to, or changing the position of, another part, as the hammer tail of a striking clock."
          ],
          "quotes": [],
          "notes": [],
          "synonyms": []
        },
        {
          "sn": "4.",
          "fields": [],
          "defs": [
            "A tortoise; in ancient warfare, a movable roof or shed to protect besiegers; a testudo."
          ],
          "quotes": [
            "They had also all manner of gynes [engines] . . . that needful is [in] taking or sieging of castle or of city, as snails, that was naught else but hollow pavises and targets, under the which men, when they fought, were heled [protected], . . . as the snail is in his house; therefore they cleped them snails."
          ],
          "notes": [],
          "synonyms": []
        },
        {
          "sn": "5.",
          "fields": [
            "(Bot.)",
            "(Zool.)",
            "(Bot.)",
            "(Bot.)",
            "(Zool.)",
            "(Bot.)"
          ],
          "defs": [
            "The pod of the sanil clover."
          ],
          "quotes": [],
          "notes": [],
          "synonyms": []
        }
      ]
    }
  ]
}
