{
  "key": "sparing",
  "source_file": "CIDE.S",
  "record_count": 1,
  "records": [
    {
      "headword": "Sparing",
      "headword_raw": "Spar\"ing",
      "pr": "(?)",
      "pos": [
        "a.",
        "n."
      ],
      "ety": null,
      "sources": [
        "1913 Webster"
      ],
      "morph": null,
      "usage": [],
      "wordforms": [
        {
          "form": "Sparingly",
          "form_raw": "Spar\"ing*ly",
          "key": "sparingly",
          "pos": [],
          "pr": null
        },
        {
          "form": "Sparingness",
          "form_raw": "Spar\"ing*ness",
          "key": "sparingness",
          "pos": [
            "n."
          ],
          "pr": null
        }
      ],
      "entry_synonyms": [],
      "entry_fields": [],
      "senses": [
        {
          "sn": "0",
          "fields": [],
          "defs": [
            "Spare; saving; frugal; merciful."
          ],
          "quotes": [],
          "notes": [],
          "synonyms": []
        }
      ]
    }
  ]
}
