{
  "key": "strapple",
  "source_file": "CIDE.S",
  "record_count": 1,
  "records": [
    {
      "headword": "Strapple",
      "headword_raw": "Strap\"ple",
      "pr": "(?)",
      "pos": [
        "v. t."
      ],
      "ety": null,
      "sources": [
        "1913 Webster"
      ],
      "morph": null,
      "usage": [],
      "wordforms": [],
      "entry_synonyms": [],
      "entry_fields": [],
      "senses": [
        {
          "sn": "0",
          "fields": [],
          "defs": [
            "To hold or bind with, or as with, a strap; to entangle."
          ],
          "quotes": [],
          "notes": [],
          "synonyms": []
        }
      ]
    }
  ]
}
