{
  "key": "themis",
  "source_file": "CIDE.T",
  "record_count": 1,
  "records": [
    {
      "headword": "Themis",
      "headword_raw": "The\"mis",
      "pr": "(?)",
      "pos": [
        "n."
      ],
      "ety": "[L., fr. Gr. <?/, fr. <?/ that which is laid down or established by usage, law, prob. fr. <?/ to set, place.]",
      "sources": [
        "1913 Webster"
      ],
      "morph": null,
      "usage": [],
      "wordforms": [],
      "entry_synonyms": [],
      "entry_fields": [
        "(Gr. Myth.)"
      ],
      "senses": [
        {
          "sn": "0",
          "fields": [],
          "defs": [
            "The goddess of law and order; the patroness of existing rights."
          ],
          "quotes": [],
          "notes": [],
          "synonyms": []
        }
      ]
    }
  ]
}
