{
  "key": "trumpie",
  "source_file": "CIDE.T",
  "record_count": 1,
  "records": [
    {
      "headword": "Trumpie",
      "headword_raw": "Trum\"pie",
      "pr": "(?)",
      "pos": [
        "n."
      ],
      "ety": null,
      "sources": [
        "1913 Webster"
      ],
      "morph": null,
      "usage": [],
      "wordforms": [],
      "entry_synonyms": [],
      "entry_fields": [
        "(Zool.)"
      ],
      "senses": [
        {
          "sn": "0",
          "fields": [],
          "defs": [
            "The Richardson's skua (Stercorarius parasiticus)."
          ],
          "quotes": [],
          "notes": [],
          "synonyms": []
        }
      ]
    }
  ]
}
