{
  "key": "tutsan",
  "source_file": "CIDE.T",
  "record_count": 1,
  "records": [
    {
      "headword": "Tutsan",
      "headword_raw": "Tut\"san",
      "pr": "(?)",
      "pos": [
        "n."
      ],
      "ety": "[F. toutesaine; tout, toute, all (L. totus) + sain, saine, sound, healthy, L. sanus.]",
      "sources": [
        "1913 Webster"
      ],
      "morph": null,
      "usage": [],
      "wordforms": [],
      "entry_synonyms": [],
      "entry_fields": [
        "(Bot.)"
      ],
      "senses": [
        {
          "sn": "0",
          "fields": [],
          "defs": [
            "A plant of the genus Hypericum (Hypericum Androsoemum), from which a healing ointment is prepared in Spain; -- called also parkleaves."
          ],
          "quotes": [],
          "notes": [],
          "synonyms": []
        }
      ]
    }
  ]
}
