{
  "key": "unalist",
  "source_file": "CIDE.U",
  "record_count": 1,
  "records": [
    {
      "headword": "Unalist",
      "headword_raw": "U\"nal*ist",
      "pr": "(ū\"nl*st)",
      "pos": [
        "n."
      ],
      "ety": "[L. unus one.]",
      "sources": [
        "1913 Webster"
      ],
      "morph": null,
      "usage": [],
      "wordforms": [],
      "entry_synonyms": [],
      "entry_fields": [
        "(Eccl.)"
      ],
      "senses": [
        {
          "sn": "0",
          "fields": [],
          "defs": [
            "An ecclesiastic who holds but one benefice; -- distinguished from pluralist."
          ],
          "quotes": [],
          "notes": [],
          "synonyms": []
        }
      ]
    }
  ]
}
