{
  "key": "well",
  "source_file": "CIDE.W",
  "record_count": 6,
  "records": [
    {
      "headword": "Well",
      "headword_raw": "Well",
      "pr": "(?)",
      "pos": [
        "n.",
        "v. i."
      ],
      "ety": "[OE. welle, AS. wella, wylla, from weallan to well up, surge, boil; akin to D. wel a spring or fountain. <?/<?/<?/<?/. See Well, v. i.]",
      "sources": [
        "1913 Webster"
      ],
      "morph": null,
      "usage": [],
      "wordforms": [],
      "entry_synonyms": [],
      "entry_fields": [],
      "senses": [
        {
          "sn": "1.",
          "fields": [],
          "defs": [
            "An issue of water from the earth; a spring; a fountain."
          ],
          "quotes": [
            "Begin, then, sisters of the sacred well."
          ],
          "notes": [],
          "synonyms": []
        },
        {
          "sn": "2.",
          "fields": [],
          "defs": [
            "A pit or hole sunk into the earth to such a depth as to reach a supply of water, generally of a cylindrical form, and often walled with stone or bricks to prevent the earth from caving in."
          ],
          "quotes": [
            "The woman said unto him, Sir, thou hast nothing to draw with, and the well is deep."
          ],
          "notes": [],
          "synonyms": []
        },
        {
          "sn": "3.",
          "fields": [],
          "defs": [
            "A shaft made in the earth to obtain oil or brine."
          ],
          "quotes": [],
          "notes": [],
          "synonyms": []
        },
        {
          "sn": "4.",
          "fields": [],
          "defs": [
            "Fig.: A source of supply; fountain; wellspring."
          ],
          "quotes": [
            "Dan Chaucer, well of English undefiled.",
            "A well of serious thought and pure."
          ],
          "notes": [],
          "synonyms": []
        },
        {
          "sn": "5.",
          "fields": [
            "(Naut.)"
          ],
          "defs": [
            "An inclosure in the middle of a vessel's hold, around the pumps, from the bottom to the lower deck, to preserve the pumps from damage and facilitate their inspection.",
            "A compartment in the middle of the hold of a fishing vessel, made tight at the sides, but having holes perforated in the bottom to let in water for the preservation of fish alive while they are transported to market.",
            "A vertical passage in the stern into which an auxiliary screw propeller may be drawn up out of water.",
            "A depressed space in the after part of the deck; -- often called the cockpit."
          ],
          "quotes": [],
          "notes": [],
          "synonyms": []
        },
        {
          "sn": "6.",
          "fields": [
            "(Mil.)"
          ],
          "defs": [
            "A hole or excavation in the earth, in mining, from which run branches or galleries."
          ],
          "quotes": [],
          "notes": [],
          "synonyms": []
        },
        {
          "sn": "7.",
          "fields": [
            "(Arch.)"
          ],
          "defs": [
            "An opening through the floors of a building, as for a staircase or an elevator; a wellhole."
          ],
          "quotes": [],
          "notes": [],
          "synonyms": []
        },
        {
          "sn": "8.",
          "fields": [
            "(Metal.)",
            "(Naut.)",
            "(Naut.)",
            "(Arch.)"
          ],
          "defs": [
            "The lower part of a furnace, into which the metal falls."
          ],
          "quotes": [],
          "notes": [],
          "synonyms": []
        }
      ]
    },
    {
      "headword": "Well",
      "headword_raw": "Well",
      "pr": "(?)",
      "pos": [
        "v. i.",
        "imp. & p. p.",
        "p. pr. & vb. n."
      ],
      "ety": "[OE. wellen, AS. wyllan, wellan, fr. weallan; akin to OFries. walla, OS. & OHG. wallan, G. wallen, Icel. vella, G. welle, wave, OHG. wella, walm, AS. wylm; cf. L. volvere to roll, Gr. <?/ to inwrap, <?/ to roll. Cf. Voluble, Wallop to boil, Wallow, Weld of metal.]",
      "sources": [
        "1913 Webster"
      ],
      "morph": "[imp. & p. p. Welled (?); p. pr. & vb. n. Welling.]",
      "usage": [],
      "wordforms": [],
      "entry_synonyms": [],
      "entry_fields": [],
      "senses": [
        {
          "sn": "0",
          "fields": [],
          "defs": [
            "To issue forth, as water from the earth; to flow; to spring."
          ],
          "quotes": [
            "From his two springs in Gojam's sunny realm, Pure welling out, he through the lucid lake Of fair Dambea rolls his infant streams."
          ],
          "notes": [],
          "synonyms": []
        }
      ]
    },
    {
      "headword": "Well",
      "headword_raw": "Well",
      "pr": null,
      "pos": [
        "v. t."
      ],
      "ety": null,
      "sources": [
        "1913 Webster"
      ],
      "morph": null,
      "usage": [],
      "wordforms": [],
      "entry_synonyms": [],
      "entry_fields": [],
      "senses": [
        {
          "sn": "0",
          "fields": [],
          "defs": [
            "To pour forth, as from a well."
          ],
          "quotes": [],
          "notes": [],
          "synonyms": []
        }
      ]
    },
    {
      "headword": "Well",
      "headword_raw": "Well",
      "pr": null,
      "pos": [
        "adv.",
        "Compar.",
        "superl.",
        "v. t."
      ],
      "ety": "[OE. wel, AS. wel; akin to OS., OFries., & D. wel, G. wohl, OHG. wola, wela, Icel. & Dan. vel, Sw. väl, Goth. wala; originally meaning, according to one's will or wish. See Will, v. t., and cf. Wealth.]",
      "sources": [
        "1913 Webster"
      ],
      "morph": null,
      "usage": [],
      "wordforms": [],
      "entry_synonyms": [],
      "entry_fields": [],
      "senses": [
        {
          "sn": "1.",
          "fields": [],
          "defs": [
            "In a good or proper manner; justly; rightly; not ill or wickedly."
          ],
          "quotes": [
            "If thou doest not well, sin lieth at the door."
          ],
          "notes": [],
          "synonyms": []
        },
        {
          "sn": "2.",
          "fields": [],
          "defs": [
            "Suitably to one's condition, to the occasion, or to a proposed end or use; suitably; abundantly; fully; adequately; thoroughly."
          ],
          "quotes": [
            "Lot . . . beheld all the plain of Jordan, that it was well watered everywhere.",
            "WE are wellable to overcome it.",
            "She looketh well to the ways of her household.",
            "Servant of God, well done! well hast thou fought The better fight."
          ],
          "notes": [],
          "synonyms": []
        },
        {
          "sn": "3.",
          "fields": [],
          "defs": [
            "Fully or about; -- used with numbers."
          ],
          "quotes": [
            "Well nine and twenty in a company."
          ],
          "notes": [],
          "synonyms": []
        },
        {
          "sn": "4.",
          "fields": [],
          "defs": [
            "In such manner as is desirable; so as one could wish; satisfactorily; favorably; advantageously; conveniently."
          ],
          "quotes": [
            "Know In measure what the mind may well contain.",
            "All the world speaks well of you."
          ],
          "notes": [],
          "synonyms": []
        },
        {
          "sn": "5.",
          "fields": [],
          "defs": [
            "Considerably; not a little; far."
          ],
          "quotes": [
            "Abraham and Sarah were old and well stricken in age."
          ],
          "notes": [
            "☞ Well is sometimes used elliptically for it is well, as an expression of satisfaction with what has been said or done, and sometimes it expresses concession, or is merely expletive; as, well, the work is done; well, let us go; well, well, be it so.",
            "☞ Well, like above, ill, and so, is used before many participial adjectives in its usual adverbial senses, and subject to the same custom with regard to the use of the hyphen (see the Note under Ill, adv.); as, a well-affected supporter; he was well affected toward the project; a well-trained speaker; he was well trained in speaking; well-educated, or well educated; well-dressed, or well dressed; well-appearing; well-behaved; well-controlled; well-designed; well-directed; well-formed; well-meant; well-minded; well-ordered; well-performed; well-pleased; well-pleasing; well-seasoned; well-steered; well-tasted; well-told, etc. Such compound epithets usually have an obvious meaning, and since they may be formed at will, only a few of this class are given in the Vocabulary."
          ],
          "synonyms": []
        }
      ]
    },
    {
      "headword": "Well",
      "headword_raw": "Well",
      "pr": null,
      "pos": [
        "a."
      ],
      "ety": null,
      "sources": [
        "1913 Webster"
      ],
      "morph": null,
      "usage": [],
      "wordforms": [],
      "entry_synonyms": [],
      "entry_fields": [],
      "senses": [
        {
          "sn": "1.",
          "fields": [],
          "defs": [
            "Good in condition or circumstances; desirable, either in a natural or moral sense; fortunate; convenient; advantageous; happy; as, it is well for the country that the crops did not fail; it is well that the mistake was discovered."
          ],
          "quotes": [
            "It was well with us in Egypt."
          ],
          "notes": [],
          "synonyms": []
        },
        {
          "sn": "2.",
          "fields": [],
          "defs": [
            "Being in health; sound in body; not ailing, diseased, or sick; healthy; as, a well man; the patient is perfectly well."
          ],
          "quotes": [
            "Is your father well, the old man of whom ye spake?"
          ],
          "notes": [],
          "synonyms": []
        },
        {
          "sn": "3.",
          "fields": [],
          "defs": [
            "Being in favor; favored; fortunate."
          ],
          "quotes": [
            "He followed the fortunes of that family, and was well with Henry the Fourth."
          ],
          "notes": [],
          "synonyms": []
        },
        {
          "sn": "4.",
          "fields": [
            "(Marine Insurance)"
          ],
          "defs": [
            "Safe; as, a chip warranted well at a certain day and place."
          ],
          "quotes": [],
          "notes": [],
          "synonyms": []
        }
      ]
    },
    {
      "headword": "Well",
      "headword_raw": "We'll",
      "pr": "(?)",
      "pos": [],
      "ety": null,
      "sources": [
        "1913 Webster"
      ],
      "morph": null,
      "usage": [],
      "wordforms": [],
      "entry_synonyms": [],
      "entry_fields": [],
      "senses": [
        {
          "sn": "0",
          "fields": [],
          "defs": [
            "Contraction for we will or we shall."
          ],
          "quotes": [],
          "notes": [],
          "synonyms": []
        }
      ]
    }
  ]
}
